{
    "feed": [
	{
		"id":0,
		"title": "Christmas in Leicester Square",
		"category": "Events",
		"address": "Leicester Square London WC2H 7NA",
		"eventDate": "From 9th Nov 2018 until 6th Jan 2019",
		"openingTime": "12pm to 10pm Mon, Fri and 10am to 10pm Sat-Sun",
		"transport": "Leicester Square, Piccadilly Circus,Charing Cross",
		"station": "Leicester Square, Piccadilly Circus,Charing Cross",
		"bus": "24, 19, 176",
		"price": "Free Entry",
		"contact": "03333 444 167",
		"email": "access@underbelly.co.uk",
		"image": "http://www.christmasinleicestersquare.com/images/resized/images/uploads/lsqxmas_750x500.jpg",
		"description": "At the centre of London, have a traditional Christmas festival in Leicester Square.",
		"timeStamp": "1462202476000",
		"gps": "51.510435, -0.130158",
		"dateCreatedOn": "01/12/2018",
		"lastUpdatedAt": "01/12/2018",
		"url": "http://www.christmasinleicestersquare.com/your-visit",
		"runtime": "TBC"
	},
	{
		"id":1,
		"title": "Changing the Guard",
		"category": "Event",
		"address": "Buckingham Palace London SW1A 1AA",
		"eventDate": "Starts at 10.45am but get there early for a good viewing spot.",
		"openingTime": "",
		"transport": "",
		"station": "Victoria, Green Park, St Jamess Park or Hyde Park Corner",
		"bus": "",
		"price": "FREE",
		"contact": "020 3123 7321",
		"email": "bookinginfo@royalcollection.org.uk",
		"image": "http://www.trinityschoolrochester.co.uk/wp-content/uploads/2015/05/changing-the-guard.jpg",
		"description": "Changing the Guard at Buckingham Palace encompasses colourful spectacle and British pageantry. During the Changing the Guard ceremony, also known as Guard Mounting, one regiment takes over from another. The Queens Guard is made up of the St Jamess Palace and Buckingham Palace detachments. The New Guard, who during the course of the ceremony become The Queens Guard, march to Buckingham Palace from Wellington Barracks with musical accompaniment.",
		"timeStamp": "1462202476000",
		"gps": "51.5013673,-0.1440787",
		"dateCreatedOn": "20/03/2018",
		"lastUpdatedAt": "07/05/2018",
		"url": "http://www.royalcollection.org.uk",
		"runtime": "TBC"
	},
	{
		"id":2,
		"title": "Winter festival at Southbank Centre",
		"category": "Events",
		"address": "Southbank Centre, Belvedere Road, London SE1 8XX",
		"eventDate": "From 9 Nov 2018 to 6 Jan 2019",
		"openingTime": "9 Nov 2018 to 6 Jan 2019",
		"transport": "Waterloo",
		"station": "Waterloo",
		"bus": "",
		"price": "TBC",
		"contact": "020 3879 9555",
		"email": "customer@southbankcentre.co.uk",
		"image": "https://d2wq73xazpk036.cloudfront.net/media/9116038B-1451-4FB6-90B39305790096A6/B4734A55-86D2-4E9E-9B911C9075853FFC/Dynamic-94e31543-4360-5429-89ed-e3a7c57fe0f3.jpg?response-content-disposition=inline",
		"description": "See Southbank Centre transformed this winter with magical family shows, markets, twinkling lights, festive fun and other seasonal delights.",
		"timeStamp": "1462202476000",
		"gps": "51.505598, -0.116119",
		"dateCreatedOn": "01/12/2018",
		"lastUpdatedAt": "01/12/2018",
		"url": "https://www.southbankcentre.co.uk/whats-on/festivals-series/winter",
		"runtime": "TBC"
	},
	{
		"id":3,
		"title": "Christmas at Kew",
		"category": "Events",
		"address": "Kew, Richmond TW9 3AE",
		"eventDate": "On until 05 January 2019",
		"openingTime": "5pm to 10pm",
		"transport": "Kew Gardens station",
		"station": "Kew Gardens station",
		"bus": "",
		"price": "From £10 for Child Tickets and from £16.50 for Adults.",
		"contact": "020 8332 5655",
		"email": "info@kew.org",
		"image": "https://www.kew.org/sites/default/files/styles/info_block__tablet_/public/Screen%20Shot%202017-09-07%20at%2014.49.20.png",
		"description": "See the Gardens light up for an unforgettable after-dark festive trail of lights.",
		"timeStamp": "1462202476000",
		"gps": "51.478511, -0.295388",
		"dateCreatedOn": "01/12/2018",
		"lastUpdatedAt": "01/12/2018",
		"url": "https://www.kew.org/kew-gardens/whats-on/christmas-at-kew",
		"runtime": "TBC"
	},
	{
		"id":4,
		"title": "Winter Wonderland in Hyde Park",
		"category": "Events",
		"address": "Winter Wonderland Hyde Park London W2",
		"eventDate": "On until 6th January 2019",
		"openingTime": "Everyday 10am to 10pm until 6th January 2019",
		"transport": "",
		"station": "Victoria, Bond Street, Knightsbridge, Green Park, Marble Arch, Hyde Park Corner",
		"bus": "6, 7, 16, 19, 23, 36, 52, 73, 82, 98, 113, 274, 390, 414, C2,  2, 19, 36, 137, 148, 159, 436, 9, 14, 19, 22, 23, 52, 74, 94, 148, 414, 30, 38, 274",
		"price": "Entry to Winter Wonderland is free, tickets are for attrations inside.",
		"contact": "N/A",
		"email": "",
		"image": "http://www.thelevinhotel.co.uk/wp-content/uploads/2017/11/Hyde-Park-Winter-Wonderland-The-Levin.jpg",
		"description": "Celebrate Christmas at Hyde Parks Winter Wonderland, explore the many attrations including Ice Rink, The Magical Ice Kingdom, Peter Pan on Ice, Zippos Christmas Circus, Cirque Berserk, Teletubbies Christmas Show, Giant Wheel, Ice Sculpting Workshops, Winter Wonderland Comedy Club, Bar Hutte and Bar Ice.",
		"timeStamp": "1462202476000",
		"gps": "51.507162, -0.165534",
		"dateCreatedOn": "01/12/2018",
		"lastUpdatedAt": "01/12/2018",
		"url": "https://hydeparkwinterwonderland.com/",
		"runtime": "TBC"
	},
	{
		"id":5,
		"title": "Christmas tree at Trafalgar Square",
		"category": "Events",
		"address": "Trafalgar Square, London WC2N 5DN",
		"eventDate": "December until 6 January",
		"openingTime": "Everyday",
		"transport": "Leicester Square, Piccadilly Circus,Charing Cross",
		"station": "Leicester Square, Piccadilly Circus,Charing Cross",
		"bus": "3,6,12,88,139,159,453,n3,n15,n109",
		"price": "Free",
		"contact": "N/A",
		"email": "N/A",
		"image": "https://news.images.itv.com/image/file/541590/stream_img.jpg",
		"description": "The Trafalgar Square Christmas tree is a Christmas tree donated to the people of Britain by the city of Oslo, Norway each year since 1947. The tree is prominently displayed in Trafalgar Square from the beginning of December until 6 January.",
		"timeStamp": "1462202476000",
		"gps": "51.507991, -0.128054",
		"dateCreatedOn": "01/12/2018",
		"lastUpdatedAt": "01/12/2018",
		"url": "https://www.london.gov.uk/about-us/our-building-and-squares/christmas-trafalgar-square",
		"runtime": "TBC"
	},
	{
		"id":6,
		"title": "New Years Eve fireworks",
		"category": "Events",
		"address": "Thames Riverside, , Central London, SE1, United Kingdom",
		"eventDate": "Monday 31 December 2018 at 8:00pm",
		"openingTime": "8:00pm to 12:45am",
		"transport": "London Waterloo, Westminster",
		"station": "London Waterloo, Westminster",
		"bus": "",
		"price": "£10 per ticket",
		"contact": "",
		"email": "",
		"image": "https://www.london.gov.uk/sites/default/files/styles/gla_2_1_large/public/nye_2018_ldn_gov_650_1300.png",
		"description": "Watch Londons end of year spectacular display of fireworks riverside.",
		"timeStamp": "1462202476000",
		"gps": "51.502750, -0.119073",
		"dateCreatedOn": "01/12/2018",
		"lastUpdatedAt": "01/12/2018",
		"url": "https://www.london.gov.uk/events/2018-12-31/london-new-years-eve-fireworks-2018",
		"runtime": "TBC"
	}
 ]
}